biomaj2galaxy/__init__.py
biomaj2galaxy/cli.py
biomaj2galaxy/config.py
biomaj2galaxy/io.py
biomaj2galaxy/utils.py
biomaj2galaxy/commands/__init__.py
biomaj2galaxy/commands/add.py
biomaj2galaxy/commands/add_lib.py
biomaj2galaxy/commands/init.py
biomaj2galaxy/commands/rm.py
biomaj2galaxy/commands/rm_lib.py
test/__init__.py
test/dm_test.py
biomaj2galaxy-2.2.0.dist-info/LICENCE
biomaj2galaxy-2.2.0.dist-info/METADATA
biomaj2galaxy-2.2.0.dist-info/WHEEL
biomaj2galaxy-2.2.0.dist-info/entry_points.txt
biomaj2galaxy-2.2.0.dist-info/top_level.txt
biomaj2galaxy-2.2.0.dist-info/RECORD
