Metadata-Version: 2.1
Name: biomaj2galaxy
Version: 2.2.0
Summary: Command-line utility to assist in interconnecting BioMAJ (https://biomaj.genouest.org/) with Galaxy (http://galaxyproject.org/).
Home-page: https://github.com/genouest/biomaj2galaxy
Author: Anthony Bretaudeau
Author-email: anthony.bretaudeau@inra.fr
License: MIT
Platform: Posix; MacOS X; Windows
Classifier: Development Status :: 4 - Beta
Classifier: Intended Audience :: Developers
Classifier: License :: OSI Approved :: MIT License
Classifier: Operating System :: OS Independent
Classifier: Topic :: Scientific/Engineering
Classifier: Programming Language :: Python :: 3.6
Classifier: Programming Language :: Python :: 3.7
Requires-Dist: future
Requires-Dist: bioblend
Requires-Dist: click
